genomic_tokenizer/__init__.py
genomic_tokenizer/core.py
genomic_tokenizer-0.1.0.dist-info/LICENSE
genomic_tokenizer-0.1.0.dist-info/METADATA
genomic_tokenizer-0.1.0.dist-info/WHEEL
genomic_tokenizer-0.1.0.dist-info/RECORD
