Metadata-Version: 2.3
Name: genomic-tokenizer
Version: 0.1.0
Summary: Genomic Tokenizer
Author: Bell Eapen
Author-email: github_public@gulfdoctor.net
Requires-Python: >=3.10,<4.0
Classifier: Programming Language :: Python :: 3
Classifier: Programming Language :: Python :: 3.10
Classifier: Programming Language :: Python :: 3.11
Classifier: Programming Language :: Python :: 3.12
Classifier: Programming Language :: Python :: 3.13
Requires-Dist: pytest (>=8.2.1,<9.0.0)
Requires-Dist: transformers (>=4,<5)
